nonebot_plugin_chatglm6b/__init__.py
nonebot_plugin_chatglm6b/chat.py
nonebot_plugin_chatglm6b/config.py
nonebot_plugin_chatglm6b/request.py
nonebot_plugin_chatglm6b/save.py
nonebot_plugin_chatglm6b-0.1.5.dist-info/LICENSE
nonebot_plugin_chatglm6b-0.1.5.dist-info/METADATA
nonebot_plugin_chatglm6b-0.1.5.dist-info/WHEEL
nonebot_plugin_chatglm6b-0.1.5.dist-info/top_level.txt
nonebot_plugin_chatglm6b-0.1.5.dist-info/RECORD
