Metadata-Version: 2.1
Name: nonebot-plugin-chatglm6b
Version: 0.1.5
Summary: NoneBot2 plugin for ChatGLM-6B-API
Author-email: QNLanYang <117292352+QNLanYang@users.noreply.github.com>
License: GPL 3.0
Project-URL: Homepage, https://github.com/QNLanYang/nonebot_plugin_ChatGLM6B
Project-URL: Repository, https://github.com/QNLanYang/nonebot_plugin_ChatGLM6B
Requires-Python: >=3.8
License-File: LICENSE
Requires-Dist: nonebot2 (>=2.0.0rc3)
Requires-Dist: nonebot-adapter-onebot (>=2.1.5)
Requires-Dist: nonebot-plugin-htmlrender (>=0.2.0.1)
Requires-Dist: aiohttp
Requires-Dist: pydantic
Requires-Dist: aiofiles
Requires-Dist: pathlib
Requires-Dist: asyncio
